apiprotector/__init__.py
apiprotector-1.0.0.dist-info/licenses/LICENSE
apiprotector-1.0.0.dist-info/METADATA
apiprotector-1.0.0.dist-info/WHEEL
apiprotector-1.0.0.dist-info/entry_points.txt
apiprotector-1.0.0.dist-info/top_level.txt
apiprotector-1.0.0.dist-info/RECORD
