Metadata-Version: 2.4
Name: apiprotector
Version: 1.0.0
Summary: A comprehensive API protection library for Python with rate limiting, authentication, and security features
Home-page: https://github.com/phanikumar715/apiprotector
Author: Kodukulla Phani Kumar
Author-email: Kodukulla Phani Kumar <phanikumark715@gmail.com>
Maintainer-email: Kodukulla Phani Kumar <phanikumark715@gmail.com>
License: MIT
Project-URL: Homepage, https://github.com/phanikumar715/apiprotector
Project-URL: Documentation, https://apiprotector.readthedocs.io/
Project-URL: Repository, https://github.com/phanikumar715/apiprotector
Project-URL: Bug Tracker, https://github.com/phanikumar715/apiprotector/issues
Project-URL: Changelog, https://github.com/phanikumar715/apiprotector/blob/main/CHANGELOG.md
Keywords: api,protection,rate limiting,authentication,security,flask,django,fastapi,middleware,ddos,validation,throttling
Classifier: Development Status :: 5 - Production/Stable
Classifier: Intended Audience :: Developers
Classifier: Topic :: Software Development :: Libraries :: Python Modules
Classifier: Topic :: Internet :: WWW/HTTP :: HTTP Servers
Classifier: Topic :: Security
Classifier: Topic :: System :: Networking :: Monitoring
Classifier: License :: OSI Approved :: MIT License
Classifier: Programming Language :: Python :: 3
Classifier: Programming Language :: Python :: 3.6
Classifier: Programming Language :: Python :: 3.7
Classifier: Programming Language :: Python :: 3.8
Classifier: Programming Language :: Python :: 3.9
Classifier: Programming Language :: Python :: 3.10
Classifier: Programming Language :: Python :: 3.11
Classifier: Programming Language :: Python :: 3.12
Classifier: Operating System :: OS Independent
Classifier: Framework :: Flask
Classifier: Framework :: Django
Classifier: Framework :: FastAPI
Classifier: Framework :: Pyramid
Requires-Python: >=3.6
License-File: LICENSE
Provides-Extra: dev
Requires-Dist: pytest>=6.0; extra == "dev"
Requires-Dist: pytest-cov>=2.0; extra == "dev"
Requires-Dist: black>=21.0; extra == "dev"
Requires-Dist: flake8>=3.8; extra == "dev"
Requires-Dist: mypy>=0.800; extra == "dev"
Requires-Dist: pre-commit>=2.0; extra == "dev"
Requires-Dist: tox>=3.0; extra == "dev"
Provides-Extra: docs
Requires-Dist: sphinx>=4.0; extra == "docs"
Requires-Dist: sphinx-rtd-theme>=1.0; extra == "docs"
Requires-Dist: myst-parser>=0.15; extra == "docs"
Provides-Extra: test
Requires-Dist: pytest>=6.0; extra == "test"
Requires-Dist: pytest-cov>=2.0; extra == "test"
Requires-Dist: pytest-mock>=3.0; extra == "test"
Requires-Dist: coverage>=5.0; extra == "test"
Dynamic: author
Dynamic: home-page
Dynamic: license-file
Dynamic: requires-python
